reamber/__init__.py
reamber/algorithms/__init__.py
reamber/algorithms/analysis/__init__.py
reamber/algorithms/analysis/scroll_speed.py
reamber/algorithms/convert/BMSToOsu.py
reamber/algorithms/convert/BMSToQua.py
reamber/algorithms/convert/BMSToSM.py
reamber/algorithms/convert/ConvertBase.py
reamber/algorithms/convert/O2JToBMS.py
reamber/algorithms/convert/O2JToOsu.py
reamber/algorithms/convert/O2JToQua.py
reamber/algorithms/convert/O2JToSM.py
reamber/algorithms/convert/OsuToBMS.py
reamber/algorithms/convert/OsuToQua.py
reamber/algorithms/convert/OsuToSM.py
reamber/algorithms/convert/QuaToBMS.py
reamber/algorithms/convert/QuaToOsu.py
reamber/algorithms/convert/QuaToSM.py
reamber/algorithms/convert/SMToBMS.py
reamber/algorithms/convert/SMToOsu.py
reamber/algorithms/convert/SMToQua.py
reamber/algorithms/convert/__init__.py
reamber/algorithms/generate/README.md
reamber/algorithms/generate/__init__.py
reamber/algorithms/generate/full_ln.py
reamber/algorithms/generate/sv_normalize.py
reamber/algorithms/osu/__init__.py
reamber/algorithms/osu/hitsound_copy.py
reamber/algorithms/osu/parse_replay.py
reamber/algorithms/pattern/Pattern.py
reamber/algorithms/pattern/__init__.py
reamber/algorithms/pattern/combos/PtnCombo.py
reamber/algorithms/pattern/combos/_PtnCChordStream.py
reamber/algorithms/pattern/combos/_PtnCJack.py
reamber/algorithms/pattern/combos/__init__.py
reamber/algorithms/pattern/filters/PtnFilter.py
reamber/algorithms/pattern/filters/__init__.py
reamber/algorithms/playField/PlayField.py
reamber/algorithms/playField/__init__.py
reamber/algorithms/playField/parts/PFDrawBeatLines.py
reamber/algorithms/playField/parts/PFDrawBpm.py
reamber/algorithms/playField/parts/PFDrawColumnLines.py
reamber/algorithms/playField/parts/PFDrawLines.py
reamber/algorithms/playField/parts/PFDrawNotes.py
reamber/algorithms/playField/parts/PFDrawOffsets.py
reamber/algorithms/playField/parts/PFDrawSv.py
reamber/algorithms/playField/parts/PFDrawable.py
reamber-1.0.0.dist-info/LICENSE
reamber-1.0.0.dist-info/METADATA
reamber-1.0.0.dist-info/WHEEL
reamber-1.0.0.dist-info/RECORD
