Metadata-Version: 2.1
Name: reamber
Version: 1.0.0
Summary: Vertical Scrolling Rhythm Game Toolset
Author: Evening
Requires-Python: >3.9.7
Classifier: Programming Language :: Python :: 3
Classifier: Programming Language :: Python :: 3.10
Classifier: Programming Language :: Python :: 3.11
Classifier: Programming Language :: Python :: 3.12
Classifier: Programming Language :: Python :: 3.13
Requires-Dist: Pillow (>=11.0.0,<12.0.0)
Requires-Dist: PyYAML (>=6.0.1,<7.0.0)
Requires-Dist: Unidecode (>=1.3.7,<2.0.0)
Requires-Dist: matplotlib (>=3.8.0,<4.0.0)
Requires-Dist: numpy (>=1.26.1,<2.0.0)
Requires-Dist: osrparse (>=6.0.2,<7.0.0)
Requires-Dist: pandas (>=2.1.1,<3.0.0)
Requires-Dist: tqdm (>=4.67.0,<5.0.0)
